ut_wdp/__init__.py
ut_wdp/__version__.py
ut_wdp/pmeh/__init__.py
ut_wdp/pmeh/py.typed
ut_wdp/pmeh/wdp.py
ut_wdp-2.0.0.20251020.dist-info/licenses/LICENSE.txt
ut_wdp-2.0.0.20251020.dist-info/METADATA
ut_wdp-2.0.0.20251020.dist-info/WHEEL
ut_wdp-2.0.0.20251020.dist-info/top_level.txt
ut_wdp-2.0.0.20251020.dist-info/RECORD
