Metadata-Version: 2.4
Name: ut_wdp
Version: 2.0.0.20251020
Summary: Utilities for Watchdog Processors
Author-email: Bernd Stroehle <bernd.stroehle@gmail.com>
Maintainer-email: Bernd Stroehle <bernd.stroehle@gmail.com>
License-Expression: GPL-3.0-only WITH Classpath-exception-2.0 OR BSD-3-Clause
Project-URL: Source Code, https://github.com/bs2910/ut_wdp/tree/master
Project-URL: Homepage, https://kosakya.de/
Project-URL: Documentation, https://ut_wdp.readthedocs.io/en/latest
Project-URL: Apache-2.0 License, https://apache.org/licenses/LICENSE-2.0
Project-URL: GPLv3 License, https://www.gnu.org/licenses/gpl-3.0.en.html
Requires-Python: >=3.10
License-File: LICENSE.txt
Requires-Dist: ut_ctl>=1.1.2.20251008
Requires-Dist: ut_dic>=1.5.5.20251011
Requires-Dist: ut_log>=1.3.4.20251009
Requires-Dist: ut_path>=1.4.0.20251012
Requires-Dist: watchdog>=6.0.0
Dynamic: license-file
